lib/libnss_vula.so.2
vula_libnss/__init__.py
vula_libnss/__version__.py
vula_libnss-0.0.2023112400.dist-info/LICENSE
vula_libnss-0.0.2023112400.dist-info/METADATA
vula_libnss-0.0.2023112400.dist-info/WHEEL
vula_libnss-0.0.2023112400.dist-info/top_level.txt
vula_libnss-0.0.2023112400.dist-info/RECORD
