Metadata-Version: 2.1
Name: vula_libnss
Version: 0.0.2023112400
Summary: nss-altfiles for vula
Home-page: https://codeberg.org/vula/vula_libnss
Author: Vula Authors
Author-email: git@vula.link
Maintainer: Vula Authors
Maintainer-email: git@vula.link
License: GPLv3
Project-URL: Documentation, https://codeberg.org/vula/vula_libnss
Project-URL: Source, https://codeberg.org/vula/vula_libnss
Keywords: mDNS,vula,encryption,libnss
Classifier: Programming Language :: Python :: 3
Classifier: License :: OSI Approved :: GNU General Public License v3 (GPLv3)
Classifier: Operating System :: OS Independent
Requires-Python: >=3.7
License-File: LICENSE
